{
    "configurations": [
        {
            "name": "linux-gcc-x64",
            "includePath": [
                "${workspaceFolder}/**",
                "/home/serinder/GitWorkBranch/KeilMiscProject/51_18650bsmb"
            ],
            "defines": [
                "__C51__",
                "__VSCODE_C51__",
                "reentrant=",
                "compact=",
                "small=",
                "large=",
                "data=",
                "idata=",
                "pdata=",
                "bdata=",
                "xdata=",
                "code=",
                "bit=char",
                "sbit=char",
                "sfr=char",
                "sfr16=int",
                "sfr32=int",
                "interrupt=",
                "using=",
                "_at_=",
                "_priority_=",
                "_task_="
            ],
            "intelliSenseMode": "linux-gcc-x64",
            "cStandard": "${default}",
            "cppStandard": "${default}",
            "compilerPath": "/usr/bin/gcc"
        },
        {
            "name": "Target 1",
            "includePath": [
                "f:\\SYSFILE\\DeskTop\\Misc.Git\\KeilMiscProject\\51_18650_MultiChannelChargeDischargeController\\DRIVER",
                "f:\\SYSFILE\\DeskTop\\Misc.Git\\KeilMiscProject\\51_18650bsmb",
                "f:\\SYSFILE\\DeskTop\\Misc.Git\\KeilMiscProject\\51_18650_MultiChannelChargeDischargeController\\SYS",
                "D:\\Keil_v5\\C51\\INC",
                "f:\\SYSFILE\\DeskTop\\Misc.Git\\KeilMiscProject\\51_18650_MultiChannelChargeDischargeController"
            ],
            "defines": [
                "__C51__",
                "__VSCODE_C51__",
                "reentrant=",
                "compact=",
                "small=",
                "large=",
                "data=",
                "idata=",
                "pdata=",
                "bdata=",
                "xdata=",
                "code=",
                "bit=char",
                "sbit=char",
                "sfr=char",
                "sfr16=int",
                "sfr32=int",
                "interrupt=",
                "using=",
                "_at_=",
                "_priority_=",
                "_task_="
            ],
            "intelliSenseMode": "${default}"
        }
    ],
    "version": 4
}